Raiz/Versiones definitivas/Raiz/Raiz Verilog/ctrl.v
module ctrl (
    input clk,
    input rst,
    input start,
    input W_I,   // Indica si I == 0
    input W_RV,  // Indica si R >= V

    output reg reset,
    output reg shift_ops,
    output reg load_si,
    output reg load_no,
    output reg dec,
    output reg done
);

    parameter INIT        = 3'b000,
              CHECK_I     = 3'b001,
              CALC_V      = 3'b010,
              BRANCH_RV   = 3'b011,
              DEC_I       = 3'b100,
              DONE_STATE  = 3'b101;

    reg [2:0] state;

    //====================================================
    // FSM SECUENCIAL
    //====================================================
    always @(posedge clk or posedge rst) begin
        if (rst) begin
            state <= INIT;
        end
        else begin
            case (state)
                INIT: begin
                    if (start) state <= CHECK_I;
                    else       state <= INIT;
                end

                CHECK_I: begin
                    if (W_I) state <= DONE_STATE; // SI -> DONE
                    else     state <= CALC_V;      // No -> Continúa el algoritmo
                end

                CALC_V: begin
                    // Realiza síncronamente: R = (R << 2) + Bits de A
                    state <= BRANCH_RV;
                end

                BRANCH_RV: begin
                    // Dependiendo de R >= V, guardará un camino u otro
                    state <= DEC_I;
                end

                DEC_I: begin
                    // Decrementa I = I - 1 y regresa a evaluar
                    state <= CHECK_I;
                end

                DONE_STATE: begin
                    if (!start) state <= INIT;
                    else        state <= DONE_STATE;
                end

                default: state <= INIT;
            endcase
        end
    end

    //====================================================
    // LÓGICA COMBINACIONAL DE SALIDAS
    //====================================================
    always @(*) begin
        reset     = 0;
        shift_ops = 0;
        load_si   = 0;
        load_no   = 0;
        dec       = 0;
        done      = 0;

        case (state)
            INIT: begin
                reset = 1;
            end

            CALC_V: begin
                shift_ops = 1; // Hace el paso previo a comparar
            end

            BRANCH_RV: begin
                if (W_RV) load_si = 1; // SI: R = R - V; Q = (Q << 1) + 1
                else      load_no = 1; // NO: Q = Q << 1
            end

            DEC_I: begin
                dec = 1; // Resta una iteración al contador (I = I - 1)
            end

            DONE_STATE: begin
                done = 1;
            end
        endcase
    end

    `ifdef BENCH
    reg [8*40:1] state_name;
    always @(*) begin
        case(state)
            INIT       : state_name = "INIT";
            CHECK_I    : state_name = "CHECK_I";
            CALC_V     : state_name = "CALC_V";
            BRANCH_RV  : state_name = "BRANCH_RV";
            DEC_I      : state_name = "DEC_I";
            DONE_STATE : state_name = "DONE_STATE";
            default    : state_name = "UNKNOWN";
        endcase
    end
    `endif

endmodule

Raiz/Raiz/check.v
module check (
    input [3:0] I,
    output wire W_I
);

    assign W_I = (I == 4'b0000);

endmodule

Raiz/Versiones definitivas/Raiz/Raiz Verilog/cont.v
module cont (
    input clk,
    input reset,
    input dec,

    output reg [3:0] I
);

    always @(negedge clk) begin
        if (reset) begin
            I <= 4'b1000; // I = n/2 = 8 iteraciones para 16 bits
        end
        else if (dec && I != 0) begin
            I <= I - 1'b1; // I = I - 1
        end
    end

endmodule

Versiones Finales/Raiz/Raiz Verilog/op_artm.v
module op_artm (
    input [15:0] R,
    input [15:0] V,
    
    output W_RV,            // R >= V?
    output [15:0] R_resta   // R - V
);

    assign W_RV = (R >= V);
    assign R_resta = R - V;

endmodule

Raiz/Versiones definitivas/Raiz/Raiz Verilog/raiz_reg.v
module raiz_reg (
    input clk,
    input reset,
    input shift_ops,
    input load_si,
    input load_no,

    input [15:0] A_in,
    input [15:0] R_next_si,
    input [15:0] R_next_no,

    output reg [15:0] A,
    output reg [15:0] R,
    output reg [7:0]  Q,
    output [15:0] V
);

    // V = (Q << 2) + 1 combinacional
    assign V = { {6{1'b0}}, Q, 2'b00 } + 16'd1;

    always @(negedge clk) begin
        if (reset) begin
            A <= A_in; // A = n (Radicando)
            R <= 16'd0; // R = 0
            Q <= 8'd0;  // Q = 0
        end
        else if (shift_ops) begin
            // Hace el paso: R = (R << 2) + Bits de A y desplaza A hacia la izquierda 2 bits
            R <= { R[13:0], A[15:14] };
            A <= { A[13:0], 2'b00 };
        end
        else if (load_si) begin
            // Bloque SI: R = R - V y Q = (Q << 1) + 1
            R <= R_next_si;
            Q <= { Q[6:0], 1'b1 };
        end
        else if (load_no) begin
            // Bloque NO: Q = Q << 1 (
            Q <= { Q[6:0], 1'b0 };
        end
    end

endmodule

Raiz/Raiz/sqrt.v
module sqrt (
    input clk,
    input rst,
    input start,
    input [15:0] Radicando,

    output [7:0] Raiz,
    output done
);

    wire reset, shift_ops, load_si, load_no, dec;
    wire W_I, W_RV;
    
    wire [3:0]  I_count;
    wire [15:0] Reg_A;
    wire [15:0] Reg_R;
    wire [15:0] Reg_V;
    wire [15:0] R_restado;

    //========================================================
    // INSTANCIACIÓN DE LOS SUBMÓDULOS
    //========================================================

    raiz_reg raiz_reg0 (
        .clk(clk),
        .reset(reset),
        .shift_ops(shift_ops),
        .load_si(load_si),
        .load_no(load_no),
        .A_in(Radicando),
        .R_next_si(R_restado),
        .R_next_no(Reg_R),
        .A(Reg_A),
        .R(Reg_R),
        .Q(Raiz),
        .V(Reg_V)
    );

    op_artm op_artm0 (
        .R(Reg_R),
        .V(Reg_V),
        .W_RV(W_RV),
        .R_resta(R_restado)
    );

    cont cont0 (
        .clk(clk),
        .reset(reset),
        .dec(dec),
        .I(I_count)
    );

    // Conexión corregida: .W_I en lugar de .W_A
    check check0 (
        .I(I_count),
        .W_I(W_I)
    );

    ctrl ctrl0 (
        .clk(clk),
        .rst(rst),
        .start(start),
        .W_I(W_I),
        .W_RV(W_RV),
        .reset(reset),
        .shift_ops(shift_ops),
        .load_si(load_si),
        .load_no(load_no),
        .dec(dec),
        .done(done)
    );

endmodule

Raiz/Versiones definitivas/Raiz/Raiz Verilog/sqrt_TB.v
`timescale 1ns/1ps

module sqrt_TB;

    reg clk;
    reg rst;
    reg start;

    reg [15:0] Radicando; 

    wire [7:0]  Raiz;
    wire done;

    //========================================================
    // INSTANCIA DEL DUT - CORREGIDA CON EL MÓDULO DE RAÍZ CUADRADA
    //========================================================

    sqrt uut (
        .clk(clk),
        .rst(rst),
        .start(start),
        .Radicando(Radicando),
        .Raiz(Raiz),
        .done(done)
    );

    //========================================================
    // GENERADOR DE CLOCK
    //========================================================

    initial begin
        clk = 0;
        forever #5 clk = ~clk;
    end

    //========================================================
    // ESTÍMULOS
    //========================================================

    initial begin

        // Inicialización
        rst       = 1;
        start     = 0;
        Radicando = 0;

        #20;

        rst = 0;

        //====================================================
        // CASO 1: Raíz exacta
        // sqrt(144) = 12
        //====================================================

        @(negedge clk);
        Radicando = 16'd144;

        @(negedge clk);
        start = 1;

        @(negedge clk);
        start = 0;

        wait(done);

        #20;

        $display("----------------------------------");
        $display("CASO 1");
        $display("Radicando (A) = %d", Radicando);
        $display("Raiz (Q)      = %d", Raiz);
        $display("----------------------------------");

        //====================================================
        // CASO 2: Raíz exacta menor
        // sqrt(25) = 5
        //====================================================

        rst = 1;
        #20;
        rst = 0;

        @(negedge clk);
        Radicando = 16'd25;

        @(negedge clk);
        start = 1;

        @(negedge clk);
        start = 0;

        wait(done);

        #20;

        $display("----------------------------------");
        $display("CASO 2");
        $display("Radicando (A) = %d", Radicando);
        $display("Raiz (Q)      = %d", Raiz);
        $display("----------------------------------");

        //====================================================
        // CASO 3: Raíz inexacta (Truncada)
        // sqrt(10) = 3 (Ya que 3^2 = 9)
        //====================================================

        rst = 1;
        #20;
        rst = 0;

        @(negedge clk);
        Radicando = 16'd10;

        @(negedge clk);
        start = 1;

        @(negedge clk);
        start = 0;

        wait(done);

        #20;

        $display("----------------------------------");
        $display("CASO 3");
        $display("Radicando (A) = %d", Radicando);
        $display("Raiz (Q)      = %d", Raiz);
        $display("----------------------------------");

        //====================================================
        // FINALIZAR SIMULACIÓN
        //====================================================

        #100;

        $finish;

    end

    initial begin
        $dumpfile("sqrt_TB.vcd");
        $dumpvars(0, sqrt_TB);
    end

endmodule

Versiones Finales/Raiz/Raiz Verilog/sqrt_TB.vcd
$date
	Sun Jul 12 12:52:22 2026
$end
$version
	Icarus Verilog
$end
$timescale
	1ps
$end
$scope module sqrt_TB $end
$var wire 1 ! done $end
$var wire 8 " Raiz [7:0] $end
$var reg 16 # Radicando [15:0] $end
$var reg 1 $ clk $end
$var reg 1 % rst $end
$var reg 1 & start $end
$scope module uut $end
$var wire 16 ' Radicando [15:0] $end
$var wire 1 $ clk $end
$var wire 1 % rst $end
$var wire 1 & start $end
$var wire 1 ( shift_ops $end
$var wire 1 ) reset $end
$var wire 1 * load_si $end
$var wire 1 + load_no $end
$var wire 1 ! done $end
$var wire 1 , dec $end
$var wire 1 - W_RV $end
$var wire 1 . W_I $end
$var wire 16 / Reg_V [15:0] $end
$var wire 16 0 Reg_R [15:0] $end
$var wire 16 1 Reg_A [15:0] $end
$var wire 8 2 Raiz [7:0] $end
$var wire 16 3 R_restado [15:0] $end
$var wire 4 4 I_count [3:0] $end
$scope module check0 $end
$var wire 1 . W_I $end
$var wire 4 5 I [3:0] $end
$upscope $end
$scope module cont0 $end
$var wire 1 $ clk $end
$var wire 1 ) reset $end
$var wire 1 , dec $end
$var reg 4 6 I [3:0] $end
$upscope $end
$scope module ctrl0 $end
$var wire 1 . W_I $end
$var wire 1 $ clk $end
$var wire 1 % rst $end
$var wire 1 & start $end
$var wire 1 - W_RV $end
$var parameter 3 7 BRANCH_RV $end
$var parameter 3 8 CALC_V $end
$var parameter 3 9 CHECK_I $end
$var parameter 3 : DEC_I $end
$var parameter 3 ; DONE_STATE $end
$var parameter 3 < INIT $end
$var reg 1 , dec $end
$var reg 1 ! done $end
$var reg 1 + load_no $end
$var reg 1 * load_si $end
$var reg 1 ) reset $end
$var reg 1 ( shift_ops $end
$var reg 3 = state [2:0] $end
$var reg 320 > state_name [320:1] $end
$upscope $end
$scope module op_artm0 $end
$var wire 1 - W_RV $end
$var wire 16 ? V [15:0] $end
$var wire 16 @ R_resta [15:0] $end
$var wire 16 A R [15:0] $end
$upscope $end
$scope module raiz_reg0 $end
$var wire 16 B A_in [15:0] $end
$var wire 16 C R_next_no [15:0] $end
$var wire 16 D R_next_si [15:0] $end
$var wire 1 $ clk $end
$var wire 1 + load_no $end
$var wire 1 * load_si $end
$var wire 1 ) reset $end
$var wire 1 ( shift_ops $end
$var wire 16 E V [15:0] $end
$var reg 16 F A [15:0] $end
$var reg 8 G Q [7:0] $end
$var reg 16 H R [15:0] $end
$upscope $end
$upscope $end
$upscope $end
$enddefinitions $end
$comment Show the parameter values. $end
$dumpall
b0 <
b101 ;
b100 :
b1 9
b10 8
b11 7
$end
#0
$dumpvars
bx H
bx G
bx F
bx E
bx D
bx C
b0 B
bx A
bx @
bx ?
b1001001010011100100100101010100 >
b0 =
bx 6
bx 5
bx 4
bx 3
bx 2
bx 1
bx 0
bx /
x.
x-
0,
0+
0*
1)
0(
b0 '
0&
1%
0$
b0 #
bx "
0!
$end
#5000
1$
#10000
1)
0.
b1000 4
b1000 5
b1000 6
b1111111111111111 3
b1111111111111111 @
b1111111111111111 D
0-
b1 /
b1 ?
b1 E
b0 "
b0 2
b0 G
b0 0
b0 A
b0 C
b0 H
b0 1
b0 F
0$
#15000
1$
#20000
b10010000 1
b10010000 F
b10010000 #
b10010000 '
b10010000 B
0$
0%
#25000
1$
#30000
1&
0$
#35000
b1000011010010000100010101000011010010110101111101001001 >
0)
b1 =
1$
#40000
0&
0$
#45000
b10000110100000101001100010000110101111101010110 >
1(
b10 =
1$
#50000
b1001000000 1
b1001000000 F
0$
#55000
b10000100101001001000001010011100100001101001000010111110101001001010110 >
1+
0(
b11 =
1$
#60000
0$
#65000
b100010001000101010000110101111101001001 >
1,
0+
b100 =
1$
#70000
b111 4
b111 5
b111 6
0$
#75000
b1000011010010000100010101000011010010110101111101001001 >
0,
b1 =
1$
#80000
0$
#85000
b10000110100000101001100010000110101111101010110 >
1(
b10 =
1$
#90000
b100100000000 1
b100100000000 F
0$
#95000
b10000100101001001000001010011100100001101001000010111110101001001010110 >
1+
0(
b11 =
1$
#100000
0$
#105000
b100010001000101010000110101111101001001 >
1,
0+
b100 =
1$
#110000
b110 4
b110 5
b110 6
0$
#115000
b1000011010010000100010101000011010010110101111101001001 >
0,
b1 =
1$
#120000
0$
#125000
b10000110100000101001100010000110101111101010110 >
1(
b10 =
1$
#130000
b10010000000000 1
b10010000000000 F
0$
#135000
b10000100101001001000001010011100100001101001000010111110101001001010110 >
1+
0(
b11 =
1$
#140000
0$
#145000
b100010001000101010000110101111101001001 >
1,
0+
b100 =
1$
#150000
b101 4
b101 5
b101 6
0$
#155000
b1000011010010000100010101000011010010110101111101001001 >
0,
b1 =
1$
#160000
0$
#165000
b10000110100000101001100010000110101111101010110 >
1(
b10 =
1$
#170000
b1001000000000000 1
b1001000000000000 F
0$
#175000
b10000100101001001000001010011100100001101001000010111110101001001010110 >
1+
0(
b11 =
1$
#180000
0$
#185000
b100010001000101010000110101111101001001 >
1,
0+
b100 =
1$
#190000
b100 4
b100 5
b100 6
0$
#195000
b1000011010010000100010101000011010010110101111101001001 >
0,
b1 =
1$
#200000
0$
#205000
b10000110100000101001100010000110101111101010110 >
1(
b10 =
1$
#210000
1(
b100000000000000 1
b100000000000000 F
b1 3
b1 @
b1 D
1-
b10 0
b10 A
b10 C
b10 H
0$
#215000
b10000100101001001000001010011100100001101001000010111110101001001010110 >
1*
0(
b11 =
1$
#220000
1+
0*
0-
b101 /
b101 ?
b101 E
b1 "
b1 2
b1 G
b1111111111111100 3
b1111111111111100 @
b1111111111111100 D
b1 0
b1 A
b1 C
b1 H
0$
#225000
b100010001000101010000110101111101001001 >
1,
0+
b100 =
1$
#230000
b11 4
b11 5
b11 6
0$
#235000
b1000011010010000100010101000011010010110101111101001001 >
0,
b1 =
1$
#240000
0$
#245000
b10000110100000101001100010000110101111101010110 >
1(
b10 =
1$
#250000
1(
b0 1
b0 F
b0 3
b0 @
b0 D
1-
b101 0
b101 A
b101 C
b101 H
0$
#255000
b10000100101001001000001010011100100001101001000010111110101001001010110 >
1*
0(
b11 =
1$
#260000
1+
0*
b1101 /
b1101 ?
b1101 E
b11 "
b11 2
b11 G
b1111111111110011 3
b1111111111110011 @
b1111111111110011 D
0-
b0 0
b0 A
b0 C
b0 H
0$
#265000
b100010001000101010000110101111101001001 >
1,
0+
b100 =
1$
#270000
b10 4
b10 5
b10 6
0$
#275000
b1000011010010000100010101000011010010110101111101001001 >
0,
b1 =
1$
#280000
0$
#285000
b10000110100000101001100010000110101111101010110 >
1(
b10 =
1$
#290000
0$
#295000
b10000100101001001000001010011100100001101001000010111110101001001010110 >
1+
0(
b11 =
1$
#300000
b1111111111100111 3
b1111111111100111 @
b1111111111100111 D
b11001 /
b11001 ?
b11001 E
b110 "
b110 2
b110 G
0$
#305000
b100010001000101010000110101111101001001 >
1,
0+
b100 =
1$
#310000
b1 4
b1 5
b1 6
0$
#315000
b1000011010010000100010101000011010010110101111101001001 >
0,
b1 =
1$
#320000
0$
#325000
b10000110100000101001100010000110101111101010110 >
1(
b10 =
1$
#330000
0$
#335000
b10000100101001001000001010011100100001101001000010111110101001001010110 >
1+
0(
b11 =
1$
#340000
b1111111111001111 3
b1111111111001111 @
b1111111111001111 D
b110001 /
b110001 ?
b110001 E
b1100 "
b1100 2
b1100 G
0$
#345000
b100010001000101010000110101111101001001 >
1,
0+
b100 =
1$
#350000
1.
b0 4
b0 5
b0 6
0$
#355000
b1000011010010000100010101000011010010110101111101001001 >
0,
b1 =
1$
#360000
0$
#365000
b1000100010011110100111001000101010111110101001101010100010000010101010001000101 >
1!
b101 =
1$
#370000
0$
#375000
b1001001010011100100100101010100 >
1)
0!
b0 =
1$
#380000
b1111111111111111 3
b1111111111111111 @
b1111111111111111 D
b1 /
b1 ?
b1 E
b0 "
b0 2
b0 G
b10010000 1
b10010000 F
0.
b1000 4
b1000 5
b1000 6
0$
#385000
1$
1%
#390000
0$
#395000
1$
#400000
0$
#405000
1$
0%
#410000
b11001 1
b11001 F
b11001 #
b11001 '
b11001 B
0$
#415000
1$
#420000
1&
0$
#425000
b1000011010010000100010101000011010010110101111101001001 >
0)
b1 =
1$
#430000
0&
0$
#435000
b10000110100000101001100010000110101111101010110 >
1(
b10 =
1$
#440000
b1100100 1
b1100100 F
0$
#445000
b10000100101001001000001010011100100001101001000010111110101001001010110 >
1+
0(
b11 =
1$
#450000
0$
#455000
b100010001000101010000110101111101001001 >
1,
0+
b100 =
1$
#460000
b111 4
b111 5
b111 6
0$
#465000
b1000011010010000100010101000011010010110101111101001001 >
0,
b1 =
1$
#470000
0$
#475000
b10000110100000101001100010000110101111101010110 >
1(
b10 =
1$
#480000
b110010000 1
b110010000 F
0$
#485000
b10000100101001001000001010011100100001101001000010111110101001001010110 >
1+
0(
b11 =
1$
#490000
0$
#495000
b100010001000101010000110101111101001001 >
1,
0+
b100 =
1$
#500000
b110 4
b110 5
b110 6
0$
#505000
b1000011010010000100010101000011010010110101111101001001 >
0,
b1 =
1$
#510000
0$
#515000
b10000110100000101001100010000110101111101010110 >
1(
b10 =
1$
#520000
b11001000000 1
b11001000000 F
0$
#525000
b10000100101001001000001010011100100001101001000010111110101001001010110 >
1+
0(
b11 =
1$
#530000
0$
#535000
b100010001000101010000110101111101001001 >
1,
0+
b100 =
1$
#540000
b101 4
b101 5
b101 6
0$
#545000
b1000011010010000100010101000011010010110101111101001001 >
0,
b1 =
1$
#550000
0$
#555000
b10000110100000101001100010000110101111101010110 >
1(
b10 =
1$
#560000
b1100100000000 1
b1100100000000 F
0$
#565000
b10000100101001001000001010011100100001101001000010111110101001001010110 >
1+
0(
b11 =
1$
#570000
0$
#575000
b100010001000101010000110101111101001001 >
1,
0+
b100 =
1$
#580000
b100 4
b100 5
b100 6
0$
#585000
b1000011010010000100010101000011010010110101111101001001 >
0,
b1 =
1$
#590000
0$
#595000
b10000110100000101001100010000110101111101010110 >
1(
b10 =
1$
#600000
b110010000000000 1
b110010000000000 F
0$
#605000
b10000100101001001000001010011100100001101001000010111110101001001010110 >
1+
0(
b11 =
1$
#610000
0$
#615000
b100010001000101010000110101111101001001 >
1,
0+
b100 =
1$
#620000
b11 4
b11 5
b11 6
0$
#625000
b1000011010010000100010101000011010010110101111101001001 >
0,
b1 =
1$
#630000
0$
#635000
b10000110100000101001100010000110101111101010110 >
1(
b10 =
1$
#640000
1(
b1001000000000000 1
b1001000000000000 F
b0 3
b0 @
b0 D
1-
b1 0
b1 A
b1 C
b1 H
0$
#645000
b10000100101001001000001010011100100001101001000010111110101001001010110 >
1*
0(
b11 =
1$
#650000
1+
0*
b101 /
b101 ?
b101 E
b1 "
b1 2
b1 G
b1111111111111011 3
b1111111111111011 @
b1111111111111011 D
0-
b0 0
b0 A
b0 C
b0 H
0$
#655000
b100010001000101010000110101111101001001 >
1,
0+
b100 =
1$
#660000
b10 4
b10 5
b10 6
0$
#665000
b1000011010010000100010101000011010010110101111101001001 >
0,
b1 =
1$
#670000
0$
#675000
b10000110100000101001100010000110101111101010110 >
1(
b10 =
1$
#680000
b100000000000000 1
b100000000000000 F
b1111111111111101 3
b1111111111111101 @
b1111111111111101 D
b10 0
b10 A
b10 C
b10 H
0$
#685000
b10000100101001001000001010011100100001101001000010111110101001001010110 >
1+
0(
b11 =
1$
#690000
b1111111111111001 3
b1111111111111001 @
b1111111111111001 D
b1001 /
b1001 ?
b1001 E
b10 "
b10 2
b10 G
0$
#695000
b100010001000101010000110101111101001001 >
1,
0+
b100 =
1$
#700000
b1 4
b1 5
b1 6
0$
#705000
b1000011010010000100010101000011010010110101111101001001 >
0,
b1 =
1$
#710000
0$
#715000
b10000110100000101001100010000110101111101010110 >
1(
b10 =
1$
#720000
1(
b0 1
b0 F
b0 3
b0 @
b0 D
1-
b1001 0
b1001 A
b1001 C
b1001 H
0$
#725000
b10000100101001001000001010011100100001101001000010111110101001001010110 >
1*
0(
b11 =
1$
#730000
1+
0*
b10101 /
b10101 ?
b10101 E
b101 "
b101 2
b101 G
b1111111111101011 3
b1111111111101011 @
b1111111111101011 D
0-
b0 0
b0 A
b0 C
b0 H
0$
#735000
b100010001000101010000110101111101001001 >
1,
0+
b100 =
1$
#740000
1.
b0 4
b0 5
b0 6
0$
#745000
b1000011010010000100010101000011010010110101111101001001 >
0,
b1 =
1$
#750000
0$
#755000
b1000100010011110100111001000101010111110101001101010100010000010101010001000101 >
1!
b101 =
1$
#760000
0$
#765000
b1001001010011100100100101010100 >
1)
0!
b0 =
1$
#770000
0.
b1000 4
b1000 5
b1000 6
b1111111111111111 3
b1111111111111111 @
b1111111111111111 D
b1 /
b1 ?
b1 E
b0 "
b0 2
b0 G
b11001 1
b11001 F
0$
#775000
1$
1%
#780000
0$
#785000
1$
#790000
0$
#795000
1$
0%
#800000
b1010 1
b1010 F
b1010 #
b1010 '
b1010 B
0$
#805000
1$
#810000
1&
0$
#815000
b1000011010010000100010101000011010010110101111101001001 >
0)
b1 =
1$
#820000
0&
0$
#825000
b10000110100000101001100010000110101111101010110 >
1(
b10 =
1$
#830000
b101000 1
b101000 F
0$
#835000
b10000100101001001000001010011100100001101001000010111110101001001010110 >
1+
0(
b11 =
1$
#840000
0$
#845000
b100010001000101010000110101111101001001 >
1,
0+
b100 =
1$
#850000
b111 4
b111 5
b111 6
0$
#855000
b1000011010010000100010101000011010010110101111101001001 >
0,
b1 =
1$
#860000
0$
#865000
b10000110100000101001100010000110101111101010110 >
1(
b10 =
1$
#870000
b10100000 1
b10100000 F
0$
#875000
b10000100101001001000001010011100100001101001000010111110101001001010110 >
1+
0(
b11 =
1$
#880000
0$
#885000
b100010001000101010000110101111101001001 >
1,
0+
b100 =
1$
#890000
b110 4
b110 5
b110 6
0$
#895000
b1000011010010000100010101000011010010110101111101001001 >
0,
b1 =
1$
#900000
0$
#905000
b10000110100000101001100010000110101111101010110 >
1(
b10 =
1$
#910000
b1010000000 1
b1010000000 F
0$
#915000
b10000100101001001000001010011100100001101001000010111110101001001010110 >
1+
0(
b11 =
1$
#920000
0$
#925000
b100010001000101010000110101111101001001 >
1,
0+
b100 =
1$
#930000
b101 4
b101 5
b101 6
0$
#935000
b1000011010010000100010101000011010010110101111101001001 >
0,
b1 =
1$
#940000
0$
#945000
b10000110100000101001100010000110101111101010110 >
1(
b10 =
1$
#950000
b101000000000 1
b101000000000 F
0$
#955000
b10000100101001001000001010011100100001101001000010111110101001001010110 >
1+
0(
b11 =
1$
#960000
0$
#965000
b100010001000101010000110101111101001001 >
1,
0+
b100 =
1$
#970000
b100 4
b100 5
b100 6
0$
#975000
b1000011010010000100010101000011010010110101111101001001 >
0,
b1 =
1$
#980000
0$
#985000
b10000110100000101001100010000110101111101010110 >
1(
b10 =
1$
#990000
b10100000000000 1
b10100000000000 F
0$
#995000
b10000100101001001000001010011100100001101001000010111110101001001010110 >
1+
0(
b11 =
1$
#1000000
0$
#1005000
b100010001000101010000110101111101001001 >
1,
0+
b100 =
1$
#1010000
b11 4
b11 5
b11 6
0$
#1015000
b1000011010010000100010101000011010010110101111101001001 >
0,
b1 =
1$
#1020000
0$
#1025000
b10000110100000101001100010000110101111101010110 >
1(
b10 =
1$
#1030000
b1010000000000000 1
b1010000000000000 F
0$
#1035000
b10000100101001001000001010011100100001101001000010111110101001001010110 >
1+
0(
b11 =
1$
#1040000
0$
#1045000
b100010001000101010000110101111101001001 >
1,
0+
b100 =
1$
#1050000
b10 4
b10 5
b10 6
0$
#1055000
b1000011010010000100010101000011010010110101111101001001 >
0,
b1 =
1$
#1060000
0$
#1065000
b10000110100000101001100010000110101111101010110 >
1(
b10 =
1$
#1070000
1(
b1000000000000000 1
b1000000000000000 F
b1 3
b1 @
b1 D
1-
b10 0
b10 A
b10 C
b10 H
0$
#1075000
b10000100101001001000001010011100100001101001000010111110101001001010110 >
1*
0(
b11 =
1$
#1080000
1+
0*
0-
b101 /
b101 ?
b101 E
b1 "
b1 2
b1 G
b1111111111111100 3
b1111111111111100 @
b1111111111111100 D
b1 0
b1 A
b1 C
b1 H
0$
#1085000
b100010001000101010000110101111101001001 >
1,
0+
b100 =
1$
#1090000
b1 4
b1 5
b1 6
0$
#1095000
b1000011010010000100010101000011010010110101111101001001 >
0,
b1 =
1$
#1100000
0$
#1105000
b10000110100000101001100010000110101111101010110 >
1(
b10 =
1$
#1110000
1(
b0 1
b0 F
b1 3
b1 @
b1 D
1-
b110 0
b110 A
b110 C
b110 H
0$
#1115000
b10000100101001001000001010011100100001101001000010111110101001001010110 >
1*
0(
b11 =
1$
#1120000
1+
0*
b1101 /
b1101 ?
b1101 E
b11 "
b11 2
b11 G
b1111111111110100 3
b1111111111110100 @
b1111111111110100 D
0-
b1 0
b1 A
b1 C
b1 H
0$
#1125000
b100010001000101010000110101111101001001 >
1,
0+
b100 =
1$
#1130000
1.
b0 4
b0 5
b0 6
0$
#1135000
b1000011010010000100010101000011010010110101111101001001 >
0,
b1 =
1$
#1140000
0$
#1145000
b1000100010011110100111001000101010111110101001101010100010000010101010001000101 >
1!
b101 =
1$
#1150000
0$
#1155000
b1001001010011100100100101010100 >
1)
0!
b0 =
1$
#1160000
b1 /
b1 ?
b1 E
b0 "
b0 2
b0 G
b1111111111111111 3
b1111111111111111 @
b1111111111111111 D
b0 0
b0 A
b0 C
b0 H
b1010 1
b1010 F
0.
b1000 4
b1000 5
b1000 6
0$
