Versiones Finales/bintobcd/bin-bcd verilog/reg_R.v
module reg_R (clk, rst, bin_in, bcd_corr, load, shift, correct, R);
    input clk;
    input rst;
    input [15:0] bin_in;
    input [19:0] bcd_corr;
    input load;
    input shift;
    input correct;
    output reg [35:0] R;

    always @(posedge clk) begin
        if (rst)
            R <= 36'd0;
        else if (load)
            R <= {20'b0, bin_in};
        else if (correct)
            R <= {bcd_corr, R[15:0]};
        else if (shift)
            R <= R << 1;
    end
endmodule

Versiones Finales/bintobcd/bin-bcd verilog/corrector_bcd.v
module corrector_bcd (bcd_in, bcd_out);
    input [19:0] bcd_in;
    output reg [19:0] bcd_out; 

    always @(*) begin
        // Dígito 0 (Unidades)
        if (bcd_in[3:0] >= 4'd5)
            bcd_out[3:0] = bcd_in[3:0] + 4'd3;
        else
            bcd_out[3:0] = bcd_in[3:0];

        // Dígito 1 (Decenas)
        if (bcd_in[7:4] >= 4'd5)
            bcd_out[7:4] = bcd_in[7:4] + 4'd3;
        else
            bcd_out[7:4] = bcd_in[7:4];

        // Dígito 2 (Centenas)
        if (bcd_in[11:8] >= 4'd5)
            bcd_out[11:8] = bcd_in[11:8] + 4'd3;
        else
            bcd_out[11:8] = bcd_in[11:8];

        // Dígito 3 (Millares)
        if (bcd_in[15:12] >= 4'd5)
            bcd_out[15:12] = bcd_in[15:12] + 4'd3;
        else
            bcd_out[15:12] = bcd_in[15:12];

        // Dígito 4 (Decenas de millar)
        if (bcd_in[19:16] >= 4'd5)
            bcd_out[19:16] = bcd_in[19:16] + 4'd3;
        else
            bcd_out[19:16] = bcd_in[19:16];
    end

endmodule

Versiones Finales/bcdtobin/bcd-bin verilog/comp_zero.v
module comp_zero (count, z);
    input [4:0] count;
    output z;
    
    assign z = (count == 0) ? 1'b1 : 1'b0;
endmodule

Versiones Finales/bintobcd/bin-bcd verilog/contador.v
module contador (clk, rst, load, dec, count);
    input clk;
    input rst;
    input load;
    input dec;
    output reg [4:0] count;

    always @(posedge clk) begin
        if (rst)
            count <= 5'd0;
        else if (load)
            count <= 5'd16;
        else if (dec)
            count <= count - 1'b1;
    end
endmodule

Versiones Finales/bintobcd/bin-bcd verilog/ctrl.v
module ctrl( 
    input clk,
    input rst,
    input start, 
    input z,
    output reg done,
    output reg shift,
    output reg load,
    output reg dec,
    output reg correct
);

    parameter START   = 3'b000;
    parameter LOAD    = 3'b001;
    parameter SHIFT   = 3'b010;
    parameter CHECK   = 3'b011;
    parameter CORRECT = 3'b100;
    parameter END     = 3'b101;
 
    reg [2:0] state;

    // Lógica de salidas (Combinacional)
    always @(*) begin
        case(state)
            START: begin
                done    <= 0;
                shift   <= 0;
                load    <= 0;
                dec     <= 0;
                correct <= 0;
            end
            LOAD: begin
                done    <= 0;
                shift   <= 0;
                load    <= 1;
                dec     <= 0;
                correct <= 0;
            end   
            SHIFT: begin
                done    <= 0;
                shift   <= 1;
                load    <= 0;
                dec     <= 1;
                correct <= 0;
            end
            CHECK: begin
                done    <= 0;
                shift   <= 0;
                load    <= 0;
                dec     <= 0;
                correct <= 0;
            end
            CORRECT: begin
                done    <= 0;
                shift   <= 0;
                load    <= 0;
                dec     <= 0;
                correct <= 1;
            end
            END: begin
                done    <= 1;
                shift   <= 0;
                load    <= 0;
                dec     <= 0;
                correct <= 0;
            end
            default: begin
                done    <= 0;
                shift   <= 0;
                load    <= 0;
                dec     <= 0;
                correct <= 0;
            end
        endcase
    end

    // Lógica de siguiente estado (Secuencial en flanco de bajada)
    always @(negedge clk) begin
        if (rst) begin
            state <= START;
        end else begin
            case(state)
                START: begin
                    if(start)
                        state <= LOAD; 
                    else
                        state <= START; 
                end
                LOAD: begin
                    state <= SHIFT;
                end   
                SHIFT: begin
                    state <= CHECK;   
                end
                CHECK: begin
                    if (z)
                        state <= END;  
                    else 
                        state <= CORRECT;
                end
                CORRECT: begin
                    state <= SHIFT;
                end
                END: begin
                    if(start)
                        state <= END;
                    else
                        state <= START; 
                end
                default: state <= START;
            endcase
        end
    end
endmodule

Versiones Finales/bintobcd/bin-bcd verilog/bintobcd.v
module bintobcd (
    input clk,
    input rst,
    input start,
    input [15:0] bin_in,
    output done,
    output [19:0] bcd_out
);

    wire z_wire;
    wire load_wire, shift_wire, dec_wire, correct_wire;
    wire [4:0] count_wire;
    wire [35:0] R_wire;
    wire [19:0] bcd_corr_wire;

    assign bcd_out = R_wire[35:16];

    ctrl U_CTRL (
        .clk     (clk),
        .rst     (rst),
        .start   (start),
        .z       (z_wire),
        .done    (done),
        .shift   (shift_wire),
        .load    (load_wire),
        .dec     (dec_wire),
        .correct (correct_wire)
    );

    contador U_CONT (
        .clk   (clk),
        .rst   (rst),
        .load  (load_wire),
        .dec   (dec_wire),
        .count (count_wire)
    );

    comp_zero U_COMP (
        .count (count_wire),
        .z     (z_wire)
    );

    corrector_bcd U_CORR (
        .bcd_in  (R_wire[35:16]),
        .bcd_out (bcd_corr_wire)
    );

    reg_R U_REG (
        .clk      (clk),
        .rst      (rst),
        .bin_in   (bin_in),
        .bcd_corr (bcd_corr_wire),
        .load     (load_wire),
        .shift    (shift_wire),
        .correct  (correct_wire),
        .R        (R_wire)
    );

endmodule

Versiones Finales/bintobcd/bin-bcd verilog/bintobcd_tb.v
`timescale 1ns / 1ps

module bintobcd_tb;

    reg         clk;
    reg         rst;
    reg         start;
    reg  [15:0] bin_in;

    wire        done;
    wire [19:0] bcd_out;
    
    wire [3:0]  digit4 = bcd_out[19:16];
    wire [3:0]  digit3 = bcd_out[15:12];
    wire [3:0]  digit2 = bcd_out[11:8];
    wire [3:0]  digit1 = bcd_out[7:4];
    wire [3:0]  digit0 = bcd_out[3:0];

    bintobcd uut (
        .clk     (clk),
        .rst     (rst),
        .start   (start),
        .bin_in  (bin_in),
        .done    (done),
        .bcd_out (bcd_out)
    );

    always begin
        #5 clk = ~clk;
    end

    initial begin
        $dumpfile("bintobcd_tb.vcd");
        $dumpvars(0, bintobcd_tb);

        clk    = 0;
        rst    = 1;
        start  = 0;
        bin_in = 16'd0;

        #20;
        rst = 0;
        #10;

        $display("[TB] --- Iniciando Caso 1: bin_in = 45 ---");
        bin_in = 16'd45;
        start  = 1;
        #10;
        start  = 0;

        @(posedge done);
        #1; 
        $display("[RESULTADO] Bin: %d -> BCD: %h%h%h%h%h (Esperado: 00045)", 
                  bin_in, digit4, digit3, digit2, digit1, digit0);
        #20;

        $display("[TB] --- Iniciando Caso 2: bin_in = 12345 ---");
        bin_in = 16'd12345;
        start  = 1;
        #10;
        start  = 0;

        @(posedge done);
        #1;
        $display("[RESULTADO] Bin: %d -> BCD: %h%h%h%h%h (Esperado: 12345)", 
                  bin_in, digit4, digit3, digit2, digit1, digit0);
        #20;

        $display("[TB] --- Iniciando Caso 3: bin_in = 65535 ---");
        bin_in = 16'hFFFF; // 65535 en decimal
        start  = 1;
        #10;
        start  = 0;

        @(posedge done);
        #1;
        $display("[RESULTADO] Bin: %d -> BCD: %h%h%h%h%h (Esperado: 65535)", 
                  bin_in, digit4, digit3, digit2, digit1, digit0);
        
        #40;
        $display("[TB] --- Simulación Finalizada Exitosamente ---");
        $finish;
    end

endmodule

Versiones Finales/bintobcd/bin-bcd verilog/bintobcd_tb.vcd
$date
	Tue Jul 14 18:46:22 2026
$end
$version
	Icarus Verilog
$end
$timescale
	1ps
$end
$scope module bintobcd_tb $end
$var wire 1 ! done $end
$var wire 4 " digit4 [3:0] $end
$var wire 4 # digit3 [3:0] $end
$var wire 4 $ digit2 [3:0] $end
$var wire 4 % digit1 [3:0] $end
$var wire 4 & digit0 [3:0] $end
$var wire 20 ' bcd_out [19:0] $end
$var reg 16 ( bin_in [15:0] $end
$var reg 1 ) clk $end
$var reg 1 * rst $end
$var reg 1 + start $end
$scope module uut $end
$var wire 16 , bin_in [15:0] $end
$var wire 1 ) clk $end
$var wire 1 * rst $end
$var wire 1 + start $end
$var wire 1 - z_wire $end
$var wire 1 . shift_wire $end
$var wire 1 / load_wire $end
$var wire 1 ! done $end
$var wire 1 0 dec_wire $end
$var wire 5 1 count_wire [4:0] $end
$var wire 1 2 correct_wire $end
$var wire 20 3 bcd_out [19:0] $end
$var wire 20 4 bcd_corr_wire [19:0] $end
$var wire 36 5 R_wire [35:0] $end
$scope module U_COMP $end
$var wire 1 - z $end
$var wire 5 6 count [4:0] $end
$upscope $end
$scope module U_CONT $end
$var wire 1 ) clk $end
$var wire 1 * rst $end
$var wire 1 / load $end
$var wire 1 0 dec $end
$var reg 5 7 count [4:0] $end
$upscope $end
$scope module U_CORR $end
$var wire 20 8 bcd_in [19:0] $end
$var reg 20 9 bcd_out [19:0] $end
$upscope $end
$scope module U_CTRL $end
$var wire 1 ) clk $end
$var wire 1 * rst $end
$var wire 1 + start $end
$var wire 1 - z $end
$var parameter 3 : CHECK $end
$var parameter 3 ; CORRECT $end
$var parameter 3 < END $end
$var parameter 3 = LOAD $end
$var parameter 3 > SHIFT $end
$var parameter 3 ? START $end
$var reg 1 2 correct $end
$var reg 1 0 dec $end
$var reg 1 ! done $end
$var reg 1 / load $end
$var reg 1 . shift $end
$var reg 3 @ state [2:0] $end
$upscope $end
$scope module U_REG $end
$var wire 20 A bcd_corr [19:0] $end
$var wire 16 B bin_in [15:0] $end
$var wire 1 ) clk $end
$var wire 1 2 correct $end
$var wire 1 / load $end
$var wire 1 * rst $end
$var wire 1 . shift $end
$var reg 36 C R [35:0] $end
$upscope $end
$upscope $end
$upscope $end
$enddefinitions $end
$comment Show the parameter values. $end
$dumpall
b0 ?
b10 >
b1 =
b101 <
b100 ;
b11 :
$end
#0
$dumpvars
bx C
b0 B
bx A
b0 @
bx 9
bx 8
bx 7
bx 6
bx 5
bx 4
bx 3
02
bx 1
00
0/
0.
x-
b0 ,
0+
1*
0)
b0 (
bx '
bx &
bx %
bx $
bx #
bx "
0!
$end
#5000
b0 4
b0 9
b0 A
b0 &
b0 %
b0 $
b0 #
b0 "
1-
b0 8
b0 '
b0 3
b0 1
b0 6
b0 7
b0 5
b0 C
1)
#10000
0)
#15000
1)
#20000
0)
0*
#25000
1)
#30000
1/
b1 @
0)
1+
b101101 (
b101101 ,
b101101 B
#35000
0-
b101101 5
b101101 C
b10000 1
b10000 6
b10000 7
1)
#40000
10
0/
1.
b10 @
0)
0+
#45000
b1111 1
b1111 6
b1111 7
b1011010 5
b1011010 C
1)
#50000
00
0.
b11 @
0)
#55000
1)
#60000
12
b100 @
0)
#65000
1)
#70000
02
10
1.
b10 @
0)
#75000
b10110100 5
b10110100 C
b1110 1
b1110 6
b1110 7
1)
#80000
00
0.
b11 @
0)
#85000
1)
#90000
12
b100 @
0)
#95000
1)
#100000
02
10
1.
b10 @
0)
#105000
b1101 1
b1101 6
b1101 7
b101101000 5
b101101000 C
1)
#110000
00
0.
b11 @
0)
#115000
1)
#120000
12
b100 @
0)
#125000
1)
#130000
02
10
1.
b10 @
0)
#135000
b1011010000 5
b1011010000 C
b1100 1
b1100 6
b1100 7
1)
#140000
00
0.
b11 @
0)
#145000
1)
#150000
12
b100 @
0)
#155000
1)
#160000
02
10
1.
b10 @
0)
#165000
b1011 1
b1011 6
b1011 7
b10110100000 5
b10110100000 C
1)
#170000
00
0.
b11 @
0)
#175000
1)
#180000
12
b100 @
0)
#185000
1)
#190000
02
10
1.
b10 @
0)
#195000
b101101000000 5
b101101000000 C
b1010 1
b1010 6
b1010 7
1)
#200000
00
0.
b11 @
0)
#205000
1)
#210000
12
b100 @
0)
#215000
1)
#220000
02
10
1.
b10 @
0)
#225000
b1001 1
b1001 6
b1001 7
b1011010000000 5
b1011010000000 C
1)
#230000
00
0.
b11 @
0)
#235000
1)
#240000
12
b100 @
0)
#245000
1)
#250000
02
10
1.
b10 @
0)
#255000
b10110100000000 5
b10110100000000 C
b1000 1
b1000 6
b1000 7
1)
#260000
00
0.
b11 @
0)
#265000
1)
#270000
12
b100 @
0)
#275000
1)
#280000
02
10
1.
b10 @
0)
#285000
b111 1
b111 6
b111 7
b101101000000000 5
b101101000000000 C
1)
#290000
00
0.
b11 @
0)
#295000
1)
#300000
12
b100 @
0)
#305000
1)
#310000
02
10
1.
b10 @
0)
#315000
b1011010000000000 5
b1011010000000000 C
b110 1
b110 6
b110 7
1)
#320000
00
0.
b11 @
0)
#325000
1)
#330000
12
b100 @
0)
#335000
1)
#340000
02
10
1.
b10 @
0)
#345000
b1 4
b1 9
b1 A
b1 &
b1 8
b1 '
b1 3
b101 1
b101 6
b101 7
b10110100000000000 5
b10110100000000000 C
1)
#350000
00
0.
b11 @
0)
#355000
1)
#360000
12
b100 @
0)
#365000
1)
#370000
02
10
1.
b10 @
0)
#375000
b10 4
b10 9
b10 A
b10 &
b10 8
b10 '
b10 3
b101101000000000000 5
b101101000000000000 C
b100 1
b100 6
b100 7
1)
#380000
00
0.
b11 @
0)
#385000
1)
#390000
12
b100 @
0)
#395000
1)
#400000
02
10
1.
b10 @
0)
#405000
b1000 4
b1000 9
b1000 A
b101 &
b101 8
b101 '
b101 3
b11 1
b11 6
b11 7
b1011010000000000000 5
b1011010000000000000 C
1)
#410000
00
0.
b11 @
0)
#415000
1)
#420000
12
b100 @
0)
#425000
b1011 4
b1011 9
b1011 A
b1000 &
b1000 8
b1000 '
b1000 3
b10001010000000000000 5
b10001010000000000000 C
1)
#430000
02
10
1.
b10 @
0)
#435000
b10001 4
b10001 9
b10001 A
b1 &
b1 %
b10001 8
b10001 '
b10001 3
b100010100000000000000 5
b100010100000000000000 C
b10 1
b10 6
b10 7
1)
#440000
00
0.
b11 @
0)
#445000
1)
#450000
12
b100 @
0)
#455000
1)
#460000
02
10
1.
b10 @
0)
#465000
b100010 4
b100010 9
b100010 A
b10 &
b10 %
b100010 8
b100010 '
b100010 3
b1 1
b1 6
b1 7
b1000101000000000000000 5
b1000101000000000000000 C
1)
#470000
00
0.
b11 @
0)
#475000
1)
#480000
12
b100 @
0)
#485000
1)
#490000
02
10
1.
b10 @
0)
#495000
b1001000 4
b1001000 9
b1001000 A
b101 &
b100 %
b1000101 8
b1000101 '
b1000101 3
1-
b10001010000000000000000 5
b10001010000000000000000 C
b0 1
b0 6
b0 7
1)
#500000
00
0.
b11 @
0)
#505000
1)
#510000
1!
b101 @
0)
#515000
1)
#520000
0!
b0 @
0)
#525000
1)
#530000
0)
#531000
1+
b11000000111001 (
b11000000111001 ,
b11000000111001 B
#535000
1)
#540000
1/
b1 @
0)
#541000
0+
#545000
b0 4
b0 9
b0 A
b0 &
b0 %
0-
b0 8
b0 '
b0 3
b10000 1
b10000 6
b10000 7
b11000000111001 5
b11000000111001 C
1)
#550000
10
0/
1.
b10 @
0)
#555000
b110000001110010 5
b110000001110010 C
b1111 1
b1111 6
b1111 7
1)
#560000
00
0.
b11 @
0)
#565000
1)
#570000
12
b100 @
0)
#575000
1)
#580000
02
10
1.
b10 @
0)
#585000
b1110 1
b1110 6
b1110 7
b1100000011100100 5
b1100000011100100 C
1)
#590000
00
0.
b11 @
0)
#595000
1)
#600000
12
b100 @
0)
#605000
1)
#610000
02
10
1.
b10 @
0)
#615000
b1 4
b1 9
b1 A
b1 &
b1 8
b1 '
b1 3
b11000000111001000 5
b11000000111001000 C
b1101 1
b1101 6
b1101 7
1)
#620000
00
0.
b11 @
0)
#625000
1)
#630000
12
b100 @
0)
#635000
1)
#640000
02
10
1.
b10 @
0)
#645000
b11 4
b11 9
b11 A
b11 &
b11 8
b11 '
b11 3
b1100 1
b1100 6
b1100 7
b110000001110010000 5
b110000001110010000 C
1)
#650000
00
0.
b11 @
0)
#655000
1)
#660000
12
b100 @
0)
#665000
1)
#670000
02
10
1.
b10 @
0)
#675000
b1001 4
b1001 9
b1001 A
b110 &
b110 8
b110 '
b110 3
b1100000011100100000 5
b1100000011100100000 C
b1011 1
b1011 6
b1011 7
1)
#680000
00
0.
b11 @
0)
#685000
1)
#690000
12
b100 @
0)
#695000
b1100 4
b1100 9
b1100 A
b1001 &
b1001 8
b1001 '
b1001 3
b10010000011100100000 5
b10010000011100100000 C
1)
#700000
02
10
1.
b10 @
0)
#705000
b10010 4
b10010 9
b10010 A
b10 &
b1 %
b10010 8
b10010 '
b10010 3
b1010 1
b1010 6
b1010 7
b100100000111001000000 5
b100100000111001000000 C
1)
#710000
00
0.
b11 @
0)
#715000
1)
#720000
12
b100 @
0)
#725000
1)
#730000
02
10
1.
b10 @
0)
#735000
b100100 4
b100100 9
b100100 A
b100 &
b10 %
b100100 8
b100100 '
b100100 3
b1001000001110010000000 5
b1001000001110010000000 C
b1001 1
b1001 6
b1001 7
1)
#740000
00
0.
b11 @
0)
#745000
1)
#750000
12
b100 @
0)
#755000
1)
#760000
02
10
1.
b10 @
0)
#765000
b1001011 4
b1001011 9
b1001011 A
b1000 &
b100 %
b1001000 8
b1001000 '
b1001000 3
b1000 1
b1000 6
b1000 7
b10010000011100100000000 5
b10010000011100100000000 C
1)
#770000
00
0.
b11 @
0)
#775000
1)
#780000
12
b100 @
0)
#785000
b1001110 4
b1001110 9
b1001110 A
b1011 &
b1001011 8
b1001011 '
b1001011 3
b10010110011100100000000 5
b10010110011100100000000 C
1)
#790000
02
10
1.
b10 @
0)
#795000
b11001001 4
b11001001 9
b11001001 A
b110 &
b1001 %
b10010110 8
b10010110 '
b10010110 3
b100101100111001000000000 5
b100101100111001000000000 C
b111 1
b111 6
b111 7
1)
#800000
00
0.
b11 @
0)
#805000
1)
#810000
12
b100 @
0)
#815000
b11111100 4
b11111100 9
b11111100 A
b1001 &
b1100 %
b11001001 8
b11001001 '
b11001001 3
b110010010111001000000000 5
b110010010111001000000000 C
1)
#820000
02
10
1.
b10 @
0)
#825000
b111000010 4
b111000010 9
b111000010 A
b10 &
b1001 %
b1 $
b110010010 8
b110010010 '
b110010010 3
b110 1
b110 6
b110 7
b1100100101110010000000000 5
b1100100101110010000000000 C
1)
#830000
00
0.
b11 @
0)
#835000
1)
#840000
12
b100 @
0)
#845000
b111110010 4
b111110010 9
b111110010 A
b1100 %
b111000010 8
b111000010 '
b111000010 3
b1110000101110010000000000 5
b1110000101110010000000000 C
1)
#850000
02
10
1.
b10 @
0)
#855000
b1110111000 4
b1110111000 9
b1110111000 A
b101 &
b1000 %
b11 $
b1110000101 8
b1110000101 '
b1110000101 3
b11100001011100100000000000 5
b11100001011100100000000000 C
b101 1
b101 6
b101 7
1)
#860000
00
0.
b11 @
0)
#865000
1)
#870000
12
b100 @
0)
#875000
b1111101011 4
b1111101011 9
b1111101011 A
b1000 &
b1011 %
b1110111000 8
b1110111000 '
b1110111000 3
b11101110001100100000000000 5
b11101110001100100000000000 C
1)
#880000
02
10
1.
b10 @
0)
#885000
b101010100001 4
b101010100001 9
b101010100001 A
b1 &
b111 %
b111 $
b11101110001 8
b11101110001 '
b11101110001 3
b100 1
b100 6
b100 7
b111011100011001000000000000 5
b111011100011001000000000000 C
1)
#890000
00
0.
b11 @
0)
#895000
1)
#900000
12
b100 @
0)
#905000
b110111010001 4
b110111010001 9
b110111010001 A
b1010 %
b1010 $
b101010100001 8
b101010100001 '
b101010100001 3
b1010101000011001000000000000 5
b1010101000011001000000000000 C
1)
#910000
02
10
1.
b10 @
0)
#915000
b1100001000011 4
b1100001000011 9
b1100001000011 A
b11 &
b100 %
b101 $
b1 #
b1010101000011 8
b1010101000011 '
b1010101000011 3
b10101010000110010000000000000 5
b10101010000110010000000000000 C
b11 1
b11 6
b11 7
1)
#920000
00
0.
b11 @
0)
#925000
1)
#930000
12
b100 @
0)
#935000
b1101101000011 4
b1101101000011 9
b1101101000011 A
b1000 $
b1100001000011 8
b1100001000011 '
b1100001000011 3
b11000010000110010000000000000 5
b11000010000110010000000000000 C
1)
#940000
02
10
1.
b10 @
0)
#945000
b11000010111001 4
b11000010111001 9
b11000010111001 A
b110 &
b1000 %
b0 $
b11 #
b11000010000110 8
b11000010000110 '
b11000010000110 3
b10 1
b10 6
b10 7
b110000100001100100000000000000 5
b110000100001100100000000000000 C
1)
#950000
00
0.
b11 @
0)
#955000
1)
#960000
12
b100 @
0)
#965000
b11000011101100 4
b11000011101100 9
b11000011101100 A
b1001 &
b1011 %
b11000010111001 8
b11000010111001 '
b11000010111001 3
b110000101110010100000000000000 5
b110000101110010100000000000000 C
1)
#970000
02
10
1.
b10 @
0)
#975000
b1001000110100010 4
b1001000110100010 9
b1001000110100010 A
b10 &
b111 %
b1 $
b110 #
b110000101110010 8
b110000101110010 '
b110000101110010 3
b1100001011100101000000000000000 5
b1100001011100101000000000000000 C
b1 1
b1 6
b1 7
1)
#980000
00
0.
b11 @
0)
#985000
1)
#990000
12
b100 @
0)
#995000
b1100000111010010 4
b1100000111010010 9
b1100000111010010 A
b1010 %
b1001 #
b1001000110100010 8
b1001000110100010 '
b1001000110100010 3
b10010001101000101000000000000000 5
b10010001101000101000000000000000 C
1)
#1000000
02
10
1.
b10 @
0)
#1005000
b10010001101001000 4
b10010001101001000 9
b10010001101001000 A
b101 &
b100 %
b11 $
b10 #
b1 "
1-
b10010001101000101 8
b10010001101000101 '
b10010001101000101 3
b0 1
b0 6
b0 7
b100100011010001010000000000000000 5
b100100011010001010000000000000000 C
1)
#1010000
00
0.
b11 @
0)
#1015000
1)
#1020000
1!
b101 @
0)
#1025000
1)
#1030000
0!
b0 @
0)
#1035000
1)
#1040000
0)
#1041000
1+
b1111111111111111 (
b1111111111111111 ,
b1111111111111111 B
#1045000
1)
#1050000
1/
b1 @
0)
#1051000
0+
#1055000
b0 4
b0 9
b0 A
b0 &
b0 %
b0 $
b0 #
b0 "
b0 8
b0 '
b0 3
0-
b1111111111111111 5
b1111111111111111 C
b10000 1
b10000 6
b10000 7
1)
#1060000
10
0/
1.
b10 @
0)
#1065000
b1 4
b1 9
b1 A
b1 &
b1 8
b1 '
b1 3
b1111 1
b1111 6
b1111 7
b11111111111111110 5
b11111111111111110 C
1)
#1070000
00
0.
b11 @
0)
#1075000
1)
#1080000
12
b100 @
0)
#1085000
1)
#1090000
02
10
1.
b10 @
0)
#1095000
b11 4
b11 9
b11 A
b11 &
b11 8
b11 '
b11 3
b111111111111111100 5
b111111111111111100 C
b1110 1
b1110 6
b1110 7
1)
#1100000
00
0.
b11 @
0)
#1105000
1)
#1110000
12
b100 @
0)
#1115000
1)
#1120000
02
10
1.
b10 @
0)
#1125000
b1010 4
b1010 9
b1010 A
b111 &
b111 8
b111 '
b111 3
b1101 1
b1101 6
b1101 7
b1111111111111111000 5
b1111111111111111000 C
1)
#1130000
00
0.
b11 @
0)
#1135000
1)
#1140000
12
b100 @
0)
#1145000
b1101 4
b1101 9
b1101 A
b1010 &
b1010 8
b1010 '
b1010 3
b10101111111111111000 5
b10101111111111111000 C
1)
#1150000
02
10
1.
b10 @
0)
#1155000
b11000 4
b11000 9
b11000 A
b101 &
b1 %
b10101 8
b10101 '
b10101 3
b101011111111111110000 5
b101011111111111110000 C
b1100 1
b1100 6
b1100 7
1)
#1160000
00
0.
b11 @
0)
#1165000
1)
#1170000
12
b100 @
0)
#1175000
b11011 4
b11011 9
b11011 A
b1000 &
b11000 8
b11000 '
b11000 3
b110001111111111110000 5
b110001111111111110000 C
1)
#1180000
02
10
1.
b10 @
0)
#1185000
b110001 4
b110001 9
b110001 A
b1 &
b11 %
b110001 8
b110001 '
b110001 3
b1011 1
b1011 6
b1011 7
b1100011111111111100000 5
b1100011111111111100000 C
1)
#1190000
00
0.
b11 @
0)
#1195000
1)
#1200000
12
b100 @
0)
#1205000
1)
#1210000
02
10
1.
b10 @
0)
#1215000
b10010011 4
b10010011 9
b10010011 A
b11 &
b110 %
b1100011 8
b1100011 '
b1100011 3
b11000111111111111000000 5
b11000111111111111000000 C
b1010 1
b1010 6
b1010 7
1)
#1220000
00
0.
b11 @
0)
#1225000
1)
#1230000
12
b100 @
0)
#1235000
b11000011 4
b11000011 9
b11000011 A
b1001 %
b10010011 8
b10010011 '
b10010011 3
b100100111111111111000000 5
b100100111111111111000000 C
1)
#1240000
02
10
1.
b10 @
0)
#1245000
b100101010 4
b100101010 9
b100101010 A
b111 &
b10 %
b1 $
b100100111 8
b100100111 '
b100100111 3
b1001 1
b1001 6
b1001 7
b1001001111111111110000000 5
b1001001111111111110000000 C
1)
#1250000
00
0.
b11 @
0)
#1255000
1)
#1260000
12
b100 @
0)
#1265000
b100101101 4
b100101101 9
b100101101 A
b1010 &
b100101010 8
b100101010 '
b100101010 3
b1001010101111111110000000 5
b1001010101111111110000000 C
1)
#1270000
02
10
1.
b10 @
0)
#1275000
b1010001000 4
b1010001000 9
b1010001000 A
b101 &
b101 %
b10 $
b1001010101 8
b1001010101 '
b1001010101 3
b10010101011111111100000000 5
b10010101011111111100000000 C
b1000 1
b1000 6
b1000 7
1)
#1280000
00
0.
b11 @
0)
#1285000
1)
#1290000
12
b100 @
0)
#1295000
b1010111011 4
b1010111011 9
b1010111011 A
b1000 &
b1000 %
b1010001000 8
b1010001000 '
b1010001000 3
b10100010001111111100000000 5
b10100010001111111100000000 C
1)
#1300000
02
10
1.
b10 @
0)
#1305000
b100000010001 4
b100000010001 9
b100000010001 A
b1 &
b1 %
b101 $
b10100010001 8
b10100010001 '
b10100010001 3
b111 1
b111 6
b111 7
b101000100011111111000000000 5
b101000100011111111000000000 C
1)
#1310000
00
0.
b11 @
0)
#1315000
1)
#1320000
12
b100 @
0)
#1325000
b101100010001 4
b101100010001 9
b101100010001 A
b1000 $
b100000010001 8
b100000010001 '
b100000010001 3
b1000000100011111111000000000 5
b1000000100011111111000000000 C
1)
#1330000
02
10
1.
b10 @
0)
#1335000
b1000000100011 4
b1000000100011 9
b1000000100011 A
b11 &
b10 %
b0 $
b1 #
b1000000100011 8
b1000000100011 '
b1000000100011 3
b10000001000111111110000000000 5
b10000001000111111110000000000 C
b110 1
b110 6
b110 7
1)
#1340000
00
0.
b11 @
0)
#1345000
1)
#1350000
12
b100 @
0)
#1355000
1)
#1360000
02
10
1.
b10 @
0)
#1365000
b10000001001010 4
b10000001001010 9
b10000001001010 A
b111 &
b100 %
b10 #
b10000001000111 8
b10000001000111 '
b10000001000111 3
b101 1
b101 6
b101 7
b100000010001111111100000000000 5
b100000010001111111100000000000 C
1)
#1370000
00
0.
b11 @
0)
#1375000
1)
#1380000
12
b100 @
0)
#1385000
b10000001001101 4
b10000001001101 9
b10000001001101 A
b1010 &
b10000001001010 8
b10000001001010 '
b10000001001010 3
b100000010010101111100000000000 5
b100000010010101111100000000000 C
1)
#1390000
02
10
1.
b10 @
0)
#1395000
b100000011001000 4
b100000011001000 9
b100000011001000 A
b101 &
b1001 %
b100 #
b100000010010101 8
b100000010010101 '
b100000010010101 3
b1000000100101011111000000000000 5
b1000000100101011111000000000000 C
b100 1
b100 6
b100 7
1)
#1400000
00
0.
b11 @
0)
#1405000
1)
#1410000
12
b100 @
0)
#1415000
b100000011111011 4
b100000011111011 9
b100000011111011 A
b1000 &
b1100 %
b100000011001000 8
b100000011001000 '
b100000011001000 3
b1000000110010001111000000000000 5
b1000000110010001111000000000000 C
1)
#1420000
02
10
1.
b10 @
0)
#1425000
b1011000111000001 4
b1011000111000001 9
b1011000111000001 A
b1 &
b1001 %
b1 $
b1000 #
b1000000110010001 8
b1000000110010001 '
b1000000110010001 3
b11 1
b11 6
b11 7
b10000001100100011110000000000000 5
b10000001100100011110000000000000 C
1)
#1430000
00
0.
b11 @
0)
#1435000
1)
#1440000
12
b100 @
0)
#1445000
b1110000111110001 4
b1110000111110001 9
b1110000111110001 A
b1100 %
b1011 #
b1011000111000001 8
b1011000111000001 '
b1011000111000001 3
b10110001110000011110000000000000 5
b10110001110000011110000000000000 C
1)
#1450000
02
10
1.
b10 @
0)
#1455000
b11001001110110011 4
b11001001110110011 9
b11001001110110011 A
b11 &
b1000 %
b11 $
b110 #
b1 "
b10110001110000011 8
b10110001110000011 '
b10110001110000011 3
b101100011100000111100000000000000 5
b101100011100000111100000000000000 C
b10 1
b10 6
b10 7
1)
#1460000
00
0.
b11 @
0)
#1465000
1)
#1470000
12
b100 @
0)
#1475000
b11100001111100011 4
b11100001111100011 9
b11100001111100011 A
b1011 %
b1001 #
b11001001110110011 8
b11001001110110011 '
b11001001110110011 3
b110010011101100111100000000000000 5
b110010011101100111100000000000000 C
1)
#1480000
02
10
1.
b10 @
0)
#1485000
b110010101010011010 4
b110010101010011010 9
b110010101010011010 A
b111 &
b110 %
b111 $
b10 #
b11 "
b110010011101100111 8
b110010011101100111 '
b110010011101100111 3
b1 1
b1 6
b1 7
b1100100111011001111000000000000000 5
b1100100111011001111000000000000000 C
1)
#1490000
00
0.
b11 @
0)
#1495000
1)
#1500000
12
b100 @
0)
#1505000
b110010110111001101 4
b110010110111001101 9
b110010110111001101 A
b1010 &
b1001 %
b1010 $
b110010101010011010 8
b110010101010011010 '
b110010101010011010 3
b1100101010100110101000000000000000 5
b1100101010100110101000000000000000 C
1)
#1510000
02
10
1.
b10 @
0)
#1515000
b10011000100000111000 4
b10011000100000111000 9
b10011000100000111000 A
b101 &
b11 %
b101 $
b101 #
b110 "
b1100101010100110101 8
b1100101010100110101 '
b1100101010100110101 3
1-
b11001010101001101010000000000000000 5
b11001010101001101010000000000000000 C
b0 1
b0 6
b0 7
1)
#1520000
00
0.
b11 @
0)
#1525000
1)
#1530000
1!
b101 @
0)
#1535000
1)
#1540000
0!
b0 @
0)
