Versiones Finales/bcdtobin/bcd-bin verilog/reg_R.v
module reg_R (clk, rst, bcd_in, bcd_corr, load, shift, correct, R);
    input clk;
    input rst;
    input [19:0] bcd_in;
    input [19:0] bcd_corr;
    input load;
    input shift;
    input correct;
    output reg [35:0] R;

    always @(posedge clk) begin
        if (rst)
            R <= 36'd0;
        else if (load)
            R <= {bcd_in, 16'd0}; // R = {BCD, BIN=0}
        else if (correct)
            R <= {bcd_corr, R[15:0]}; // Se actualiza solo la parte BCD
        else if (shift)
            R <= R >> 1; // Corrimiento a la derecha
    end
endmodule

Versiones Finales/bcdtobin/bcd-bin verilog/corrector_bin.v
module corrector_bin (bcd_in, bcd_out);
    input [19:0] bcd_in;
    output reg [19:0] bcd_out;

    always @(*) begin
        // Dígito 0 (Unidades BCD)
        if (bcd_in[3:0] >= 4'd8)
            bcd_out[3:0] = bcd_in[3:0] - 4'd3;
        else
            bcd_out[3:0] = bcd_in[3:0];

        // Dígito 1 (Decenas BCD)
        if (bcd_in[7:4] >= 4'd8)
            bcd_out[7:4] = bcd_in[7:4] - 4'd3;
        else
            bcd_out[7:4] = bcd_in[7:4];

        // Dígito 2 (Centenas BCD)
        if (bcd_in[11:8] >= 4'd8)
            bcd_out[11:8] = bcd_in[11:8] - 4'd3;
        else
            bcd_out[11:8] = bcd_in[11:8];

        // Dígito 3 (Millares BCD)
        if (bcd_in[15:12] >= 4'd8)
            bcd_out[15:12] = bcd_in[15:12] - 4'd3;
        else
            bcd_out[15:12] = bcd_in[15:12];

        // Dígito 4 (Decenas de millar BCD)
        if (bcd_in[19:16] >= 4'd8)
            bcd_out[19:16] = bcd_in[19:16] - 4'd3;
        else
            bcd_out[19:16] = bcd_in[19:16];
    end
endmodule

Versiones Finales/bcdtobin/bcd-bin verilog/comp_zero.v
module comp_zero (count, z);
    input [4:0] count;
    output z;
    
    assign z = (count == 0) ? 1'b1 : 1'b0;
endmodule

Versiones Finales/bcdtobin/bcd-bin verilog/contador.v
module contador (clk, rst, load, dec, count);
    input clk;
    input rst;
    input load;
    input dec;
    output reg [4:0] count;

    always @(posedge clk) begin
        if (rst)
            count <= 5'd0;
        else if (load)
            count <= 5'd16; // 16 desplazamientos para 16 bits de salida
        else if (dec)
            count <= count - 1'b1;
    end
endmodule

Versiones Finales/bcdtobin/bcd-bin verilog/ctrl.v
module ctrl ( 
    input clk,
    input rst,
    input start, 
    input z,
    output reg done,
    output reg shift,
    output reg load,
    output reg dec,
    output reg correct
);

    parameter START   = 3'b000;
    parameter LOAD    = 3'b001;
    parameter CHECK   = 3'b010;
    parameter CORRECT = 3'b011;
    parameter SHIFT   = 3'b100;
    parameter END     = 3'b101;
 
    reg [2:0] state;

    // Lógica de salidas (Combinacional)
    always @(*) begin
        case(state)
            START: begin
                done    = 0;
                shift   = 0;
                load    = 0;
                dec     = 0;
                correct = 0;
            end
            LOAD: begin
                done    = 0;
                shift   = 0;
                load    = 1;
                dec     = 0;
                correct = 0;
            end
            CHECK: begin
                done    = 0;
                shift   = 0;
                load    = 0;
                dec     = 0;
                correct = 0;
            end
            CORRECT: begin
                done    = 0;
                shift   = 0;
                load    = 0;
                dec     = 0;
                correct = 1;
            end
            SHIFT: begin
                done    = 0;
                shift   = 1;
                load    = 0;
                dec     = 1;
                correct = 0;
            end
            END: begin
                done    = 1;
                shift   = 0;
                load    = 0;
                dec     = 0;
                correct = 0;
            end
            default: begin
                done    = 0;
                shift   = 0;
                load    = 0;
                dec     = 0;
                correct = 0;
            end
        endcase
    end

    // Lógica de siguiente estado (Secuencial en flanco de bajada)
    always @(negedge clk) begin
        if (rst) begin
            state <= START;
        end else begin
            case(state)
                START: begin
                    if(start)
                        state <= LOAD; 
                    else
                        state <= START; 
                end
                LOAD: begin
                    state <= CHECK; // Según el diagrama, de LOAD pasa a evaluar si el contador es 0
                end   
                CHECK: begin
                    if (z)
                        state <= END;  
                    else 
                        state <= CORRECT;
                end
                CORRECT: begin
                    state <= SHIFT;
                end
                SHIFT: begin
                    state <= CHECK; // Después de desplazar, vuelve a evaluar   
                end
                END: begin
                    if(start)
                        state <= END;
                    else
                        state <= START; 
                end
                default: state <= START;
            endcase
        end
    end
endmodule

Versiones Finales/bcdtobin/bcd-bin verilog/bcd2bin.v
module bcd2bin (
    input clk,
    input rst,
    input start,
    input [19:0] bcd_in, 
    output done,
    output [15:0] bin_out 
);

    // Cables de interconexión
    wire z_wire;
    wire load_wire, shift_wire, dec_wire, correct_wire;
    wire [4:0] count_wire;
    wire [35:0] R_wire;
    wire [19:0] bcd_corr_wire;

    assign bin_out = R_wire[15:0];

    ctrl U_CTRL (
        .clk     (clk),
        .rst     (rst),
        .start   (start),
        .z       (z_wire),
        .done    (done),
        .shift   (shift_wire),
        .load    (load_wire),
        .dec     (dec_wire),
        .correct (correct_wire)
    );

    contador U_CONT (
        .clk   (clk),
        .rst   (rst),
        .load  (load_wire),
        .dec   (dec_wire),
        .count (count_wire)
    );

    comp_zero U_COMP (
        .count (count_wire),
        .z     (z_wire)
    );

    corrector_bin U_CORR (
        .bcd_in  (R_wire[35:16]),
        .bcd_out (bcd_corr_wire)
    );

    reg_R U_REG (
        .clk      (clk),
        .rst      (rst),
        .bcd_in   (bcd_in),
        .bcd_corr (bcd_corr_wire),
        .load     (load_wire),
        .shift    (shift_wire),
        .correct  (correct_wire),
        .R        (R_wire)
    );

endmodule

Versiones Finales/bcdtobin/bcd-bin verilog/bcd2bin_tb.v
`timescale 1ns / 1ps
`define SIMULATION

module bcd2bin_TB;


    reg         clk;
    reg         rst;
    reg         start;
    reg  [19:0] bcd_in;

    wire        done;
    wire [15:0] bin_out;

    bcd2bin uut( 
        .clk(clk), 
        .rst(rst), 
        .start(start), 
        .bcd_in(bcd_in),
        .done(done),
        .bin_out(bin_out)
    );

    parameter PERIOD          = 20;
    parameter real DUTY_CYCLE = 0.5;
    parameter OFFSET          = 0;

    initial  begin  // Process for clk
        #OFFSET;
        forever
        begin
            clk = 1'b0;
            #(PERIOD-(PERIOD*DUTY_CYCLE)) clk = 1'b1;
            #(PERIOD*DUTY_CYCLE);
        end
    end


    initial begin
        #0 rst = 1; start = 0; bcd_in = 20'h00000;
        @(posedge clk);
        rst  = 0;
        @(posedge clk);

        @(posedge clk);
        bcd_in = 20'h12345;
        start  = 1;
        @(posedge clk);
        start  = 0;
        
        @(posedge done); 
        #(PERIOD * 3);   

        @(posedge clk);
        bcd_in = 20'h00045;
        start  = 1;
        @(posedge clk);
        start  = 0;
        
        @(posedge done);
        #(PERIOD * 3);

        @(posedge clk);
        bcd_in = 20'h65535;
        start  = 1;
        @(posedge clk);
        start  = 0;
        
        @(posedge done);
        #(PERIOD * 3);
        
        $finish; 
    end

    initial begin: TEST_CASE
        $dumpfile("bcd2bin_tb.vcd");
        $dumpvars(-1, uut);
        #(15000) $finish;
    end

endmodule

Versiones Finales/bcdtobin/bcd-bin verilog/bcd2bin_tb.vcd
$date
	Tue Jul 14 18:24:00 2026
$end
$version
	Icarus Verilog
$end
$timescale
	1ps
$end
$scope module bcd2bin_TB $end
$scope module uut $end
$var wire 20 ! bcd_in [19:0] $end
$var wire 1 " clk $end
$var wire 1 # rst $end
$var wire 1 $ start $end
$var wire 1 % z_wire $end
$var wire 1 & shift_wire $end
$var wire 1 ' load_wire $end
$var wire 1 ( done $end
$var wire 1 ) dec_wire $end
$var wire 5 * count_wire [4:0] $end
$var wire 1 + correct_wire $end
$var wire 16 , bin_out [15:0] $end
$var wire 20 - bcd_corr_wire [19:0] $end
$var wire 36 . R_wire [35:0] $end
$scope module U_COMP $end
$var wire 1 % z $end
$var wire 5 / count [4:0] $end
$upscope $end
$scope module U_CONT $end
$var wire 1 " clk $end
$var wire 1 # rst $end
$var wire 1 ' load $end
$var wire 1 ) dec $end
$var reg 5 0 count [4:0] $end
$upscope $end
$scope module U_CORR $end
$var wire 20 1 bcd_in [19:0] $end
$var reg 20 2 bcd_out [19:0] $end
$upscope $end
$scope module U_CTRL $end
$var wire 1 " clk $end
$var wire 1 # rst $end
$var wire 1 $ start $end
$var wire 1 % z $end
$var parameter 3 3 CHECK $end
$var parameter 3 4 CORRECT $end
$var parameter 3 5 END $end
$var parameter 3 6 LOAD $end
$var parameter 3 7 SHIFT $end
$var parameter 3 8 START $end
$var reg 1 + correct $end
$var reg 1 ) dec $end
$var reg 1 ( done $end
$var reg 1 ' load $end
$var reg 1 & shift $end
$var reg 3 9 state [2:0] $end
$upscope $end
$scope module U_REG $end
$var wire 20 : bcd_corr [19:0] $end
$var wire 20 ; bcd_in [19:0] $end
$var wire 1 " clk $end
$var wire 1 + correct $end
$var wire 1 ' load $end
$var wire 1 # rst $end
$var wire 1 & shift $end
$var reg 36 < R [35:0] $end
$upscope $end
$upscope $end
$upscope $end
$enddefinitions $end
$comment Show the parameter values. $end
$dumpall
b0 8
b100 7
b1 6
b101 5
b11 4
b10 3
$end
#0
$dumpvars
bx <
b0 ;
bx :
b0 9
bx 2
bx 1
bx 0
bx /
bx .
bx -
bx ,
0+
bx *
0)
0(
0'
0&
x%
0$
1#
0"
b0 !
$end
#10000
0#
1"
#20000
0"
#30000
1"
#40000
0"
#50000
1$
b10010001101000101 !
b10010001101000101 ;
1"
#60000
1'
b1 9
0"
#70000
b10010001101000101 -
b10010001101000101 2
b10010001101000101 :
b10010001101000101 1
b0 ,
0%
b100100011010001010000000000000000 .
b100100011010001010000000000000000 <
b10000 *
b10000 /
b10000 0
0$
1"
#80000
0'
b10 9
0"
#90000
1"
#100000
1+
b11 9
0"
#110000
1"
#120000
0+
1)
1&
b100 9
0"
#130000
b110000101110010 -
b110000101110010 2
b110000101110010 :
b1001000110100010 1
b1000000000000000 ,
b1111 *
b1111 /
b1111 0
b10010001101000101000000000000000 .
b10010001101000101000000000000000 <
1"
#140000
0)
0&
b10 9
0"
#150000
1"
#160000
1+
b11 9
0"
#170000
b110000101110010 1
b1100001011100101000000000000000 .
b1100001011100101000000000000000 <
1"
#180000
0+
1)
1&
b100 9
0"
#190000
b11000010000110 -
b11000010000110 2
b11000010000110 :
b11000010111001 1
b100000000000000 ,
b110000101110010100000000000000 .
b110000101110010100000000000000 <
b1110 *
b1110 /
b1110 0
1"
#200000
0)
0&
b10 9
0"
#210000
1"
#220000
1+
b11 9
0"
#230000
b11000001010110 -
b11000001010110 2
b11000001010110 :
b11000010000110 1
b110000100001100100000000000000 .
b110000100001100100000000000000 <
1"
#240000
0+
1)
1&
b100 9
0"
#250000
b1010101000011 -
b1010101000011 2
b1010101000011 :
b1100001000011 1
b10000000000000 ,
b1101 *
b1101 /
b1101 0
b11000010000110010000000000000 .
b11000010000110010000000000000 <
1"
#260000
0)
0&
b10 9
0"
#270000
1"
#280000
1+
b11 9
0"
#290000
b1010101000011 1
b10101010000110010000000000000 .
b10101010000110010000000000000 <
1"
#300000
0+
1)
1&
b100 9
0"
#310000
b11101110001 -
b11101110001 2
b11101110001 :
b101010100001 1
b1001000000000000 ,
b1010101000011001000000000000 .
b1010101000011001000000000000 <
b1100 *
b1100 /
b1100 0
1"
#320000
0)
0&
b10 9
0"
#330000
1"
#340000
1+
b11 9
0"
#350000
b11101110001 1
b111011100011001000000000000 .
b111011100011001000000000000 <
1"
#360000
0+
1)
1&
b100 9
0"
#370000
b1110000101 -
b1110000101 2
b1110000101 :
b1110111000 1
b1100100000000000 ,
b1011 *
b1011 /
b1011 0
b11101110001100100000000000 .
b11101110001100100000000000 <
1"
#380000
0)
0&
b10 9
0"
#390000
1"
#400000
1+
b11 9
0"
#410000
b1101010101 -
b1101010101 2
b1101010101 :
b1110000101 1
b11100001011100100000000000 .
b11100001011100100000000000 <
1"
#420000
0+
1)
1&
b100 9
0"
#430000
b110010010 -
b110010010 2
b110010010 :
b111000010 1
b1110010000000000 ,
b1110000101110010000000000 .
b1110000101110010000000000 <
b1010 *
b1010 /
b1010 0
1"
#440000
0)
0&
b10 9
0"
#450000
1"
#460000
1+
b11 9
0"
#470000
b101100010 -
b101100010 2
b101100010 :
b110010010 1
b1100100101110010000000000 .
b1100100101110010000000000 <
1"
#480000
0+
1)
1&
b100 9
0"
#490000
b10010110 -
b10010110 2
b10010110 :
b11001001 1
b111001000000000 ,
b1001 *
b1001 /
b1001 0
b110010010111001000000000 .
b110010010111001000000000 <
1"
#500000
0)
0&
b10 9
0"
#510000
1"
#520000
1+
b11 9
0"
#530000
b1100110 -
b1100110 2
b1100110 :
b10010110 1
b100101100111001000000000 .
b100101100111001000000000 <
1"
#540000
0+
1)
1&
b100 9
0"
#550000
b1001000 -
b1001000 2
b1001000 :
b1001011 1
b11100100000000 ,
b10010110011100100000000 .
b10010110011100100000000 <
b1000 *
b1000 /
b1000 0
1"
#560000
0)
0&
b10 9
0"
#570000
1"
#580000
1+
b11 9
0"
#590000
b1000101 -
b1000101 2
b1000101 :
b1001000 1
b10010000011100100000000 .
b10010000011100100000000 <
1"
#600000
0+
1)
1&
b100 9
0"
#610000
b100100 -
b100100 2
b100100 :
b100100 1
b1110010000000 ,
b111 *
b111 /
b111 0
b1001000001110010000000 .
b1001000001110010000000 <
1"
#620000
0)
0&
b10 9
0"
#630000
1"
#640000
1+
b11 9
0"
#650000
1"
#660000
0+
1)
1&
b100 9
0"
#670000
b10010 -
b10010 2
b10010 :
b10010 1
b111001000000 ,
b100100000111001000000 .
b100100000111001000000 <
b110 *
b110 /
b110 0
1"
#680000
0)
0&
b10 9
0"
#690000
1"
#700000
1+
b11 9
0"
#710000
1"
#720000
0+
1)
1&
b100 9
0"
#730000
b110 -
b110 2
b110 :
b1001 1
b11100100000 ,
b101 *
b101 /
b101 0
b10010000011100100000 .
b10010000011100100000 <
1"
#740000
0)
0&
b10 9
0"
#750000
1"
#760000
1+
b11 9
0"
#770000
b110 1
b1100000011100100000 .
b1100000011100100000 <
1"
#780000
0+
1)
1&
b100 9
0"
#790000
b11 -
b11 2
b11 :
b11 1
b1110010000 ,
b110000001110010000 .
b110000001110010000 <
b100 *
b100 /
b100 0
1"
#800000
0)
0&
b10 9
0"
#810000
1"
#820000
1+
b11 9
0"
#830000
1"
#840000
0+
1)
1&
b100 9
0"
#850000
b1 -
b1 2
b1 :
b1 1
b1000000111001000 ,
b11 *
b11 /
b11 0
b11000000111001000 .
b11000000111001000 <
1"
#860000
0)
0&
b10 9
0"
#870000
1"
#880000
1+
b11 9
0"
#890000
1"
#900000
0+
1)
1&
b100 9
0"
#910000
b0 -
b0 2
b0 :
b0 1
b1100000011100100 ,
b1100000011100100 .
b1100000011100100 <
b10 *
b10 /
b10 0
1"
#920000
0)
0&
b10 9
0"
#930000
1"
#940000
1+
b11 9
0"
#950000
1"
#960000
0+
1)
1&
b100 9
0"
#970000
b110000001110010 ,
b1 *
b1 /
b1 0
b110000001110010 .
b110000001110010 <
1"
#980000
0)
0&
b10 9
0"
#990000
1"
#1000000
1+
b11 9
0"
#1010000
1"
#1020000
0+
1)
1&
b100 9
0"
#1030000
b11000000111001 ,
1%
b11000000111001 .
b11000000111001 <
b0 *
b0 /
b0 0
1"
#1040000
0)
0&
b10 9
0"
#1050000
1"
#1060000
1(
b101 9
0"
#1070000
1"
#1080000
0(
b0 9
0"
#1090000
1"
#1100000
0"
#1110000
1"
#1120000
0"
#1130000
1$
b1000101 !
b1000101 ;
1"
#1140000
1'
b1 9
0"
#1150000
b1000101 -
b1000101 2
b1000101 :
b1000101 1
b0 ,
0%
b10001010000000000000000 .
b10001010000000000000000 <
b10000 *
b10000 /
b10000 0
0$
1"
#1160000
0'
b10 9
0"
#1170000
1"
#1180000
1+
b11 9
0"
#1190000
1"
#1200000
0+
1)
1&
b100 9
0"
#1210000
b100010 -
b100010 2
b100010 :
b100010 1
b1000000000000000 ,
b1111 *
b1111 /
b1111 0
b1000101000000000000000 .
b1000101000000000000000 <
1"
#1220000
0)
0&
b10 9
0"
#1230000
1"
#1240000
1+
b11 9
0"
#1250000
1"
#1260000
0+
1)
1&
b100 9
0"
#1270000
b10001 -
b10001 2
b10001 :
b10001 1
b100000000000000 ,
b100010100000000000000 .
b100010100000000000000 <
b1110 *
b1110 /
b1110 0
1"
#1280000
0)
0&
b10 9
0"
#1290000
1"
#1300000
1+
b11 9
0"
#1310000
1"
#1320000
0+
1)
1&
b100 9
0"
#1330000
b101 -
b101 2
b101 :
b1000 1
b1010000000000000 ,
b1101 *
b1101 /
b1101 0
b10001010000000000000 .
b10001010000000000000 <
1"
#1340000
0)
0&
b10 9
0"
#1350000
1"
#1360000
1+
b11 9
0"
#1370000
b101 1
b1011010000000000000 .
b1011010000000000000 <
1"
#1380000
0+
1)
1&
b100 9
0"
#1390000
b10 -
b10 2
b10 :
b10 1
b1101000000000000 ,
b101101000000000000 .
b101101000000000000 <
b1100 *
b1100 /
b1100 0
1"
#1400000
0)
0&
b10 9
0"
#1410000
1"
#1420000
1+
b11 9
0"
#1430000
1"
#1440000
0+
1)
1&
b100 9
0"
#1450000
b1 -
b1 2
b1 :
b1 1
b110100000000000 ,
b1011 *
b1011 /
b1011 0
b10110100000000000 .
b10110100000000000 <
1"
#1460000
0)
0&
b10 9
0"
#1470000
1"
#1480000
1+
b11 9
0"
#1490000
1"
#1500000
0+
1)
1&
b100 9
0"
#1510000
b0 -
b0 2
b0 :
b0 1
b1011010000000000 ,
b1011010000000000 .
b1011010000000000 <
b1010 *
b1010 /
b1010 0
1"
#1520000
0)
0&
b10 9
0"
#1530000
1"
#1540000
1+
b11 9
0"
#1550000
1"
#1560000
0+
1)
1&
b100 9
0"
#1570000
b101101000000000 ,
b1001 *
b1001 /
b1001 0
b101101000000000 .
b101101000000000 <
1"
#1580000
0)
0&
b10 9
0"
#1590000
1"
#1600000
1+
b11 9
0"
#1610000
1"
#1620000
0+
1)
1&
b100 9
0"
#1630000
b10110100000000 ,
b10110100000000 .
b10110100000000 <
b1000 *
b1000 /
b1000 0
1"
#1640000
0)
0&
b10 9
0"
#1650000
1"
#1660000
1+
b11 9
0"
#1670000
1"
#1680000
0+
1)
1&
b100 9
0"
#1690000
b1011010000000 ,
b111 *
b111 /
b111 0
b1011010000000 .
b1011010000000 <
1"
#1700000
0)
0&
b10 9
0"
#1710000
1"
#1720000
1+
b11 9
0"
#1730000
1"
#1740000
0+
1)
1&
b100 9
0"
#1750000
b101101000000 ,
b101101000000 .
b101101000000 <
b110 *
b110 /
b110 0
1"
#1760000
0)
0&
b10 9
0"
#1770000
1"
#1780000
1+
b11 9
0"
#1790000
1"
#1800000
0+
1)
1&
b100 9
0"
#1810000
b10110100000 ,
b101 *
b101 /
b101 0
b10110100000 .
b10110100000 <
1"
#1820000
0)
0&
b10 9
0"
#1830000
1"
#1840000
1+
b11 9
0"
#1850000
1"
#1860000
0+
1)
1&
b100 9
0"
#1870000
b1011010000 ,
b1011010000 .
b1011010000 <
b100 *
b100 /
b100 0
1"
#1880000
0)
0&
b10 9
0"
#1890000
1"
#1900000
1+
b11 9
0"
#1910000
1"
#1920000
0+
1)
1&
b100 9
0"
#1930000
b101101000 ,
b11 *
b11 /
b11 0
b101101000 .
b101101000 <
1"
#1940000
0)
0&
b10 9
0"
#1950000
1"
#1960000
1+
b11 9
0"
#1970000
1"
#1980000
0+
1)
1&
b100 9
0"
#1990000
b10110100 ,
b10110100 .
b10110100 <
b10 *
b10 /
b10 0
1"
#2000000
0)
0&
b10 9
0"
#2010000
1"
#2020000
1+
b11 9
0"
#2030000
1"
#2040000
0+
1)
1&
b100 9
0"
#2050000
b1011010 ,
b1 *
b1 /
b1 0
b1011010 .
b1011010 <
1"
#2060000
0)
0&
b10 9
0"
#2070000
1"
#2080000
1+
b11 9
0"
#2090000
1"
#2100000
0+
1)
1&
b100 9
0"
#2110000
b101101 ,
1%
b101101 .
b101101 <
b0 *
b0 /
b0 0
1"
#2120000
0)
0&
b10 9
0"
#2130000
1"
#2140000
1(
b101 9
0"
#2150000
1"
#2160000
0(
b0 9
0"
#2170000
1"
#2180000
0"
#2190000
1"
#2200000
0"
#2210000
1$
b1100101010100110101 !
b1100101010100110101 ;
1"
#2220000
1'
b1 9
0"
#2230000
b1100101010100110101 -
b1100101010100110101 2
b1100101010100110101 :
b1100101010100110101 1
b0 ,
0%
b11001010101001101010000000000000000 .
b11001010101001101010000000000000000 <
b10000 *
b10000 /
b10000 0
0$
1"
#2240000
0'
b10 9
0"
#2250000
1"
#2260000
1+
b11 9
0"
#2270000
1"
#2280000
0+
1)
1&
b100 9
0"
#2290000
b110010011101100111 -
b110010011101100111 2
b110010011101100111 :
b110010101010011010 1
b1000000000000000 ,
b1111 *
b1111 /
b1111 0
b1100101010100110101000000000000000 .
b1100101010100110101000000000000000 <
1"
#2300000
0)
0&
b10 9
0"
#2310000
1"
#2320000
1+
b11 9
0"
#2330000
b110010011101100111 1
b1100100111011001111000000000000000 .
b1100100111011001111000000000000000 <
1"
#2340000
0+
1)
1&
b100 9
0"
#2350000
b10110001110000011 -
b10110001110000011 2
b10110001110000011 :
b11001001110110011 1
b1100000000000000 ,
b110010011101100111100000000000000 .
b110010011101100111100000000000000 <
b1110 *
b1110 /
b1110 0
1"
#2360000
0)
0&
b10 9
0"
#2370000
1"
#2380000
1+
b11 9
0"
#2390000
b10110001101010011 -
b10110001101010011 2
b10110001101010011 :
b10110001110000011 1
b101100011100000111100000000000000 .
b101100011100000111100000000000000 <
1"
#2400000
0+
1)
1&
b100 9
0"
#2410000
b1000000110010001 -
b1000000110010001 2
b1000000110010001 :
b1011000111000001 1
b1110000000000000 ,
b1101 *
b1101 /
b1101 0
b10110001110000011110000000000000 .
b10110001110000011110000000000000 <
1"
#2420000
0)
0&
b10 9
0"
#2430000
1"
#2440000
1+
b11 9
0"
#2450000
b101000101100001 -
b101000101100001 2
b101000101100001 :
b1000000110010001 1
b10000001100100011110000000000000 .
b10000001100100011110000000000000 <
1"
#2460000
0+
1)
1&
b100 9
0"
#2470000
b100000010010101 -
b100000010010101 2
b100000010010101 :
b100000011001000 1
b1111000000000000 ,
b1000000110010001111000000000000 .
b1000000110010001111000000000000 <
b1100 *
b1100 /
b1100 0
1"
#2480000
0)
0&
b10 9
0"
#2490000
1"
#2500000
1+
b11 9
0"
#2510000
b100000001100101 -
b100000001100101 2
b100000001100101 :
b100000010010101 1
b1000000100101011111000000000000 .
b1000000100101011111000000000000 <
1"
#2520000
0+
1)
1&
b100 9
0"
#2530000
b10000001000111 -
b10000001000111 2
b10000001000111 :
b10000001001010 1
b1111100000000000 ,
b1011 *
b1011 /
b1011 0
b100000010010101111100000000000 .
b100000010010101111100000000000 <
1"
#2540000
0)
0&
b10 9
0"
#2550000
1"
#2560000
1+
b11 9
0"
#2570000
b10000001000111 1
b100000010001111111100000000000 .
b100000010001111111100000000000 <
1"
#2580000
0+
1)
1&
b100 9
0"
#2590000
b1000000100011 -
b1000000100011 2
b1000000100011 :
b1000000100011 1
b1111110000000000 ,
b10000001000111111110000000000 .
b10000001000111111110000000000 <
b1010 *
b1010 /
b1010 0
1"
#2600000
0)
0&
b10 9
0"
#2610000
1"
#2620000
1+
b11 9
0"
#2630000
1"
#2640000
0+
1)
1&
b100 9
0"
#2650000
b10100010001 -
b10100010001 2
b10100010001 :
b100000010001 1
b1111111000000000 ,
b1001 *
b1001 /
b1001 0
b1000000100011111111000000000 .
b1000000100011111111000000000 <
1"
#2660000
0)
0&
b10 9
0"
#2670000
1"
#2680000
1+
b11 9
0"
#2690000
b10100010001 1
b101000100011111111000000000 .
b101000100011111111000000000 <
1"
#2700000
0+
1)
1&
b100 9
0"
#2710000
b1001010101 -
b1001010101 2
b1001010101 :
b1010001000 1
b1111111100000000 ,
b10100010001111111100000000 .
b10100010001111111100000000 <
b1000 *
b1000 /
b1000 0
1"
#2720000
0)
0&
b10 9
0"
#2730000
1"
#2740000
1+
b11 9
0"
#2750000
b1001010101 1
b10010101011111111100000000 .
b10010101011111111100000000 <
1"
#2760000
0+
1)
1&
b100 9
0"
#2770000
b100100111 -
b100100111 2
b100100111 :
b100101010 1
b1111111110000000 ,
b111 *
b111 /
b111 0
b1001010101111111110000000 .
b1001010101111111110000000 <
1"
#2780000
0)
0&
b10 9
0"
#2790000
1"
#2800000
1+
b11 9
0"
#2810000
b100100111 1
b1001001111111111110000000 .
b1001001111111111110000000 <
1"
#2820000
0+
1)
1&
b100 9
0"
#2830000
b1100011 -
b1100011 2
b1100011 :
b10010011 1
b1111111111000000 ,
b100100111111111111000000 .
b100100111111111111000000 <
b110 *
b110 /
b110 0
1"
#2840000
0)
0&
b10 9
0"
#2850000
1"
#2860000
1+
b11 9
0"
#2870000
b1100011 1
b11000111111111111000000 .
b11000111111111111000000 <
1"
#2880000
0+
1)
1&
b100 9
0"
#2890000
b110001 -
b110001 2
b110001 :
b110001 1
b1111111111100000 ,
b101 *
b101 /
b101 0
b1100011111111111100000 .
b1100011111111111100000 <
1"
#2900000
0)
0&
b10 9
0"
#2910000
1"
#2920000
1+
b11 9
0"
#2930000
1"
#2940000
0+
1)
1&
b100 9
0"
#2950000
b10101 -
b10101 2
b10101 :
b11000 1
b1111111111110000 ,
b110001111111111110000 .
b110001111111111110000 <
b100 *
b100 /
b100 0
1"
#2960000
0)
0&
b10 9
0"
#2970000
1"
#2980000
1+
b11 9
0"
#2990000
b10101 1
b101011111111111110000 .
b101011111111111110000 <
1"
#3000000
0+
1)
1&
b100 9
0"
#3010000
b111 -
b111 2
b111 :
b1010 1
b1111111111111000 ,
b11 *
b11 /
b11 0
b10101111111111111000 .
b10101111111111111000 <
1"
#3020000
0)
0&
b10 9
0"
#3030000
1"
#3040000
1+
b11 9
0"
#3050000
b111 1
b1111111111111111000 .
b1111111111111111000 <
1"
#3060000
0+
1)
1&
b100 9
0"
#3070000
b11 -
b11 2
b11 :
b11 1
b1111111111111100 ,
b111111111111111100 .
b111111111111111100 <
b10 *
b10 /
b10 0
1"
#3080000
0)
0&
b10 9
0"
#3090000
1"
#3100000
1+
b11 9
0"
#3110000
1"
#3120000
0+
1)
1&
b100 9
0"
#3130000
b1 -
b1 2
b1 :
b1 1
b1111111111111110 ,
b1 *
b1 /
b1 0
b11111111111111110 .
b11111111111111110 <
1"
#3140000
0)
0&
b10 9
0"
#3150000
1"
#3160000
1+
b11 9
0"
#3170000
1"
#3180000
0+
1)
1&
b100 9
0"
#3190000
b0 -
b0 2
b0 :
b0 1
b1111111111111111 ,
1%
b1111111111111111 .
b1111111111111111 <
b0 *
b0 /
b0 0
1"
#3200000
0)
0&
b10 9
0"
#3210000
1"
#3220000
1(
b101 9
0"
#3230000
1"
#3240000
0(
b0 9
0"
